rustiql/.private
rustiql/LICENSE
rustiql/__init__.py
rustiql/__main__.py
rustiql/dao/__init__.py
rustiql/dao/main_dao.py
rustiql/hooking/__init__.py
rustiql/hooking/ante_build_hook.py
rustiql/hooking/ante_release_hook.py
rustiql/hooking/post_build_hook.py
rustiql/hooking/post_release_hook.py
rustiql/host/__init__.py
rustiql/host/internal_data_manager.py
rustiql/host/main_host.py
rustiql/misc/__init__.py
rustiql/misc/builder.py
rustiql/misc/default_shared_data.json
rustiql/misc/my_theme.py
rustiql/pyrustic_data/build_report.json
rustiql/pyrustic_data/hooking.json
rustiql/pyrustic_data/hubstore.json
rustiql/pyrustic_data/release_info.json
rustiql/pyrustic_data/backstage/config/build.json
rustiql/pyrustic_data/backstage/config/init.json
rustiql/pyrustic_data/backstage/config/release.json
rustiql/pyrustic_data/backstage/data/build_report.json
rustiql/pyrustic_data/backstage/data/github_release_form.json
rustiql/pyrustic_data/backstage/hooking/build.json
rustiql/pyrustic_data/backstage/hooking/init.json
rustiql/pyrustic_data/backstage/hooking/release.json
rustiql/pyrustic_data/backstage/report/build_report.json
rustiql/pyrustic_data/backstage/report/release_report.json
rustiql/pyrustic_data/hubstore/img.json
rustiql/pyrustic_data/hubstore/promotion.json
rustiql/view/__init__.py
rustiql/view/editor.py
rustiql/view/footer.py
rustiql/view/header.py
rustiql/view/main_view.py
rustiql/view/nodebar.py
rustiql/view/tree_hook.py
secret/SCRATCH.py
secret/__init__.py
tests/__init__.py
tests/__main__.py
rustiql-0.0.14.dist-info/LICENSE
rustiql-0.0.14.dist-info/METADATA
rustiql-0.0.14.dist-info/WHEEL
rustiql-0.0.14.dist-info/entry_points.txt
rustiql-0.0.14.dist-info/top_level.txt
rustiql-0.0.14.dist-info/RECORD
