Metadata-Version: 2.1
Name: rustiql
Version: 0.0.14
Summary: Graphical SQL Editor for Pyrustic
Home-page: https://github.com/pyrustic/rustiql
Author: Pyrustic Evangelist
Author-email: rusticalex@yahoo.com
Maintainer: Pyrustic Evangelist
Maintainer-email: rusticalex@yahoo.com
License: MIT
Keywords: pyrustic,graphical-sql-editor,desktop-application,tkinter,lightweight,gui,application,sql,sqlite,database,app
Platform: UNKNOWN
Classifier: Programming Language :: Python :: 3
Classifier: License :: OSI Approved :: MIT License
Classifier: Operating System :: OS Independent
Requires-Python: >=3.5
License-File: LICENSE
Requires-Dist: tkf
